tig/__init__.py
tig/modes.py
tig/prompts/environment.py
tig/prompts/objectives.py
tig/prompts/rules.py
tig/prompts/system.py
tig/prompts/system_info.py
tig/prompts/task.py
tig/prompts/tools_formatting.py
tig/prompts/tools_guidelines.py
tig/prompts/tools/apply_diff.py
tig/prompts/tools/ask_followup_question.py
tig/prompts/tools/attempt_completion.py
tig/prompts/tools/execute_command.py
tig/prompts/tools/list_code_definitions.py
tig/prompts/tools/list_files.py
tig/prompts/tools/read_file.py
tig/prompts/tools/search_files.py
tig/prompts/tools/write_to_file.py
tig/services/command_runner.py
tig/services/llms.py
tig/services/tree_sitter/parsers.py
tig/services/tree_sitter/queries/__init__.py
tig/services/tree_sitter/queries/javascript.py
tig/services/tree_sitter/queries/python.py
tig/services/tree_sitter/queries/tsx.py
tig/services/tree_sitter/queries/typescript.py
tig/tools/__init__.py
tig/tools/apply_diff.py
tig/tools/ask_followup_question.py
tig/tools/execute_command.py
tig/tools/list_code_definitions.py
tig/tools/list_files.py
tig/tools/read_file.py
tig/tools/search_files.py
tig/tools/write_to_file.py
tig/utils/intro.py
tig/utils/syntax_checker.py
tig/utils/tools.py
tig/utils/verbose.py
tig/utils/xml.py
tig/workflows/tig.py
tig_code-0.1.7.dist-info/METADATA
tig_code-0.1.7.dist-info/WHEEL
tig_code-0.1.7.dist-info/entry_points.txt
tig_code-0.1.7.dist-info/RECORD
