Metadata-Version: 2.4
Name: tig-code
Version: 0.1.7
Summary: A terminal-based AI coding agent, similar to Claude Code, OpenAI Codex etc. but works with many more LLMs.
Author-email: Rohan <rsrohan99@gmail.com>
Requires-Python: >=3.12.9
Requires-Dist: diff-match-patch>=20241021
Requires-Dist: inquirer==3.4.0
Requires-Dist: llama-index-core==0.12.28
Requires-Dist: llama-index-llms-anthropic>=0.6.10
Requires-Dist: llama-index-llms-deepseek>=0.1.1
Requires-Dist: llama-index-llms-google-genai>=0.1.9
Requires-Dist: llama-index-llms-groq>=0.3.1
Requires-Dist: llama-index-llms-ollama>=0.5.4
Requires-Dist: llama-index-llms-openai>=0.3.37
Requires-Dist: llama-index-llms-openrouter>=0.3.1
Requires-Dist: llama-index-utils-workflow>=0.3.0
Requires-Dist: llama-index==0.12.28
Requires-Dist: ordered-set==4.1.0
Requires-Dist: pathspec==0.12.1
Requires-Dist: psutil>=7.0.0
Requires-Dist: python-dotenv==1.1.0
Requires-Dist: tree-sitter-javascript>=0.23.1
Requires-Dist: tree-sitter-python>=0.23.6
Requires-Dist: tree-sitter-typescript>=0.23.2
Requires-Dist: tree-sitter>=0.24.0
Requires-Dist: tzlocal==5.3.1
